pyplan_core/__init__.py
pyplan_core/pyplan.py
pyplan_core/classes/ArrowsManager.py
pyplan_core/classes/BaseNode.py
pyplan_core/classes/DefaultNodeFormats.py
pyplan_core/classes/IOEngine.py
pyplan_core/classes/IOModule.py
pyplan_core/classes/Intellisense.py
pyplan_core/classes/Model.py
pyplan_core/classes/NodeInfo.py
pyplan_core/classes/PyplanFunctions.py
pyplan_core/classes/__init__.py
pyplan_core/classes/common/__init__.py
pyplan_core/classes/common/filterChoices.py
pyplan_core/classes/common/indexValuesReq.py
pyplan_core/classes/dynamics/BaseDynamic.py
pyplan_core/classes/dynamics/CubepyDynamic.py
pyplan_core/classes/dynamics/FactoryDynamic.py
pyplan_core/classes/dynamics/PureXArrayDynamic.py
pyplan_core/classes/dynamics/__init__.py
pyplan_core/classes/evaluators/BaseEvaluator.py
pyplan_core/classes/evaluators/BokehEvaluator.py
pyplan_core/classes/evaluators/CubepyEvaluator.py
pyplan_core/classes/evaluators/Evaluator.py
pyplan_core/classes/evaluators/IPythonEvaluator.py
pyplan_core/classes/evaluators/MatplotlibEvaluator.py
pyplan_core/classes/evaluators/NumpyEvaluator.py
pyplan_core/classes/evaluators/PandasEvaluator.py
pyplan_core/classes/evaluators/PlotlyEvaluator.py
pyplan_core/classes/evaluators/XArrayEvaluator.py
pyplan_core/classes/evaluators/__init__.py
pyplan_core/classes/wizards/BaseWizard.py
pyplan_core/classes/wizards/CalculatedField.py
pyplan_core/classes/wizards/CreateIndex.py
pyplan_core/classes/wizards/DataArrayFilter.py
pyplan_core/classes/wizards/DataarrayFromPandas.py
pyplan_core/classes/wizards/DataframeGroupby.py
pyplan_core/classes/wizards/DataframeIndex.py
pyplan_core/classes/wizards/EditIndex.py
pyplan_core/classes/wizards/IndexFromPandas.py
pyplan_core/classes/wizards/InputTable.py
pyplan_core/classes/wizards/RenameIndexItem.py
pyplan_core/classes/wizards/SelectColumns.py
pyplan_core/classes/wizards/SelectRows.py
pyplan_core/classes/wizards/__init__.py
pyplan_core/classes/wizards/sourcecsv.py
pyplan_core/classes/ws/__init__.py
pyplan_core-0.1.36.dist-info/LICENSE
pyplan_core-0.1.36.dist-info/METADATA
pyplan_core-0.1.36.dist-info/WHEEL
pyplan_core-0.1.36.dist-info/top_level.txt
pyplan_core-0.1.36.dist-info/RECORD
