Metadata-Version: 2.1
Name: pyplan-core
Version: 0.1.36
Summary: Pyplan Core is a Python library for using Pyplan models in any Python environment as for example a Jupyter Notebook.
Home-page: https://github.com/pyplan/pyplan-core
Author: Pyplan
Author-email: info@pyplan.com
License: MIT
Platform: UNKNOWN
Classifier: Environment :: Web Environment
Classifier: Intended Audience :: Developers
Classifier: Intended Audience :: End Users/Desktop
Classifier: Intended Audience :: Financial and Insurance Industry
Classifier: Operating System :: OS Independent
Classifier: License :: OSI Approved :: MIT License
Classifier: Programming Language :: Python
Classifier: Programming Language :: Python :: 3.7
Classifier: Topic :: Software Development
Classifier: Topic :: Scientific/Engineering
Requires-Dist: pytest (==5.4.1)
Requires-Dist: autopep8 (>=1.4.4)
Requires-Dist: jsonpickle (==1.2)
Requires-Dist: openpyxl (==2.6.2)
Requires-Dist: numpy (==1.17.5)
Requires-Dist: numpydoc (==0.9.1)
Requires-Dist: pandas (==0.25.3)
Requires-Dist: xarray (==0.14.1)
Requires-Dist: xlrd (==1.2.0)
